goat_plugins/jupiter/__init__.py
goat_plugins/jupiter/parameters.py
goat_plugins/jupiter/service.py
goat_sdk_plugin_jupiter-0.1.3.dist-info/METADATA
goat_sdk_plugin_jupiter-0.1.3.dist-info/WHEEL
goat_sdk_plugin_jupiter-0.1.3.dist-info/RECORD
