Metadata-Version: 2.1
Name: goat-sdk-plugin-jupiter
Version: 0.1.3
Summary: Goat plugin for jupiter
Home-page: https://ohmygoat.dev/
Keywords: goat,sdk,agents,ai,jupiter
Author: Your Name
Author-email: your_email@example.com
Requires-Python: >=3.10,<4.0
Classifier: Programming Language :: Python :: 3
Classifier: Programming Language :: Python :: 3.10
Classifier: Programming Language :: Python :: 3.11
Classifier: Programming Language :: Python :: 3.12
Requires-Dist: base58 (>=2.1)
Requires-Dist: goat-sdk (>=0.1.0,<0.2.0)
Requires-Dist: goat-sdk-wallet-solana (>=0.1.1,<0.2.0)
Project-URL: Bug Tracker, https://github.com/goat-sdk/goat/issues
Project-URL: Repository, https://github.com/goat-sdk/goat
